[
  {"id": "1", "name": "Goldfish", "type": "Freshwater", "compatibility": ["2", "3", "4"]},
  {"id": "2", "name": "Guppy", "type": "Freshwater", "compatibility": ["1", "3", "5"]},
  {"id": "3", "name": "Molly", "type": "Freshwater", "compatibility": ["1", "2", "6"]},
  {"id": "4", "name": "Betta", "type": "Freshwater", "compatibility": ["1", "7"]},
  {"id": "5", "name": "Tetra", "type": "Freshwater", "compatibility": ["2", "6", "8"]},
  {"id": "6", "name": "Platy", "type": "Freshwater", "compatibility": ["3", "5", "9"]},
  {"id": "7", "name": "Angelfish", "type": "Freshwater", "compatibility": ["4", "8", "10"]},
  {"id": "8", "name": "Discus", "type": "Freshwater", "compatibility": ["5", "7", "11"]},
  {"id": "9", "name": "Swordtail", "type": "Freshwater", "compatibility": ["6", "12"]},
  {"id": "10", "name": "Corydoras", "type": "Freshwater", "compatibility": ["7", "11", "13"]},
  {"id": "11", "name": "Oscar", "type": "Freshwater", "compatibility": ["8", "10", "14"]},
  {"id": "12", "name": "Clown Loach", "type": "Freshwater", "compatibility": ["9", "15"]},
  {"id": "13", "name": "Zebra Danio", "type": "Freshwater", "compatibility": ["10", "16"]},
  {"id": "14", "name": "Arowana", "type": "Freshwater", "compatibility": ["11", "17"]},
  {"id": "15", "name": "Catfish", "type": "Freshwater", "compatibility": ["12", "18"]},
  {"id": "16", "name": "Neon Tetra", "type": "Freshwater", "compatibility": ["13", "19"]},
  {"id": "17", "name": "Rainbowfish", "type": "Freshwater", "compatibility": ["14", "20"]},
  {"id": "18", "name": "Pufferfish", "type": "Freshwater", "compatibility": ["15", "21"]},
  {"id": "19", "name": "Killifish", "type": "Freshwater", "compatibility": ["16", "22"]},
  {"id": "20", "name": "Koi", "type": "Freshwater", "compatibility": ["17", "23"]},
  {"id": "21", "name": "Flowerhorn", "type": "Freshwater", "compatibility": ["18", "24"]},
  {"id": "22", "name": "Gourami", "type": "Freshwater", "compatibility": ["19", "25"]},
  {"id": "23", "name": "Shubunkin", "type": "Freshwater", "compatibility": ["20"]},
  {"id": "24", "name": "Pleco", "type": "Freshwater", "compatibility": ["21"]},
  {"id": "25", "name": "Tiger Barb", "type": "Freshwater", "compatibility": ["22"]}
]
